{
  "activate": true,
  "admin": {
    "email": "admin@sites.kana.sh",
    "password": "password",
    "username": "admin"
  },
  "automaticlogin": true,
  "databaseclient": "phpmyadmin",
  "environment": "local",
  "mailpit": true,
  "mariadb": "11",
  "multisite": "none",
  "php": "8.2",
  "plugins": [
    "csp-manager",
    "debug-bar",
    "disable-floc",
    "pods",
    "query-monitor",
    "rss-featured-image",
    "syntax-highlighting-code-block",
    "two-factor",
    "wordpress-seo"
  ],
  "removedefaultplugins": true,
  "scriptdebug": true,
  "ssl": true,
  "theme": "",
  "type": "theme",
  "wpdebug": true,
  "xdebug": false
}